{
    "elements": {
        "ng-include": {
            "attributes": {
                "src": {}
            }
        },
        "md-card": {
            "attributes": {
                "class": {}
            }
        },
        "md-progress-linear": {
            "attributes": {
                "md-mode": {},
                "ng-if": {},
                "class": {},
                "value": {}
            }
        },
        "md-toolbar": {
            "attributes": {
                "ng-show": {},
                "style": {},
                "class": {},
                "ng-hide": {}
            }
        },
        "md-icon": {
            "attributes": {
                "class": {}
            }
        },
        "md-sidenav": {
            "attributes": {
                "ng-show": {},
                "md-component-id": {},
                "tabindex": {},
                "ng-controller": {},
                "md-is-open": {},
                "class": {},
                "md-is-locked-open": {},
                "ng-hide": {}
            }
        },
        "md-button": {
            "attributes": {
                "hide-gt-md": {},
                "ng-href": {},
                "ng-click": {},
                "href": {},
                "type": {},
                "class": {}
            }
        },
        "md-content": {
            "attributes": {
                "class": {}
            }
        }
    },
    "attributes": {
        "layout": {},
        "hide-sm": {
            "context": "span"
        },
        "flex": {},
        "ui-view": {
            "context": "div"
        }
    }
}